cognite/airworkflow/__init__.py
cognite/airworkflow/constants.py
cognite/airworkflow/empty_matrix_checker.py
cognite/airworkflow/env_creator.py
cognite/airworkflow/file_changed.sh
cognite/airworkflow/filepaths.py
cognite/airworkflow/function_deployer.py
cognite/airworkflow/master_config.py
cognite/airworkflow/matrix_generator.py
cognite/airworkflow/matrix_generator_tester.py
cognite/airworkflow/model/__init__.py
cognite/airworkflow/model/config.py
cognite/airworkflow/model/deployment.py
cognite/airworkflow/model/project.py
cognite/airworkflow/model/schedule.py
cognite/airworkflow/model/scheduling.py
cognite/airworkflow/model_asset_hierarchy.py
cognite/airworkflow/pre_commit.py
cognite/airworkflow/run.py
cognite/airworkflow/schemas/config-schema.yaml
cognite/airworkflow/util/__init__.py
cognite/airworkflow/util/cdf.py
cognite/airworkflow/util/convert_string_times.py
cognite/airworkflow/util/cron.py
cognite/airworkflow/util/data_set_id.py
cognite/airworkflow/util/env.py
cognite/airworkflow/util/file.py
cognite/airworkflow/util/functions.py
cognite/airworkflow/util/github.py
cognite/airworkflow/util/projecthelpers.py
cognite/airworkflow/util/repoconfighelpers.py
cognite/airworkflow/util/yaml.py
cognite_air_workflow-4.0.14.dist-info/LICENSE
cognite_air_workflow-4.0.14.dist-info/WHEEL
cognite_air_workflow-4.0.14.dist-info/METADATA
cognite_air_workflow-4.0.14.dist-info/RECORD
