Metadata-Version: 2.1
Name: cognite-air-workflow
Version: 4.0.14
Summary: Client library to perform all required cognite airflow functions built to function with AIR CDF
Author: Arun Kaashyap Arunachalam
Author-email: arun.arunachalam@cognite.com
Requires-Python: >=3.7,<4.0
Classifier: Programming Language :: Python :: 3
Classifier: Programming Language :: Python :: 3.10
Classifier: Programming Language :: Python :: 3.7
Classifier: Programming Language :: Python :: 3.8
Classifier: Programming Language :: Python :: 3.9
Requires-Dist: PyGithub (>=1.51,<2.0)
Requires-Dist: cerberus (>=1.3.2,<2.0.0)
Requires-Dist: cognite-air-sdk (>=3,<4)
Requires-Dist: cognite-sdk (>=2,<3)
Requires-Dist: cognite-sdk-experimental (>=0,<1)
Requires-Dist: croniter (>=0.3.31,<0.4.0)
Requires-Dist: gitpython (>=3.1.1,<4.0.0)
Requires-Dist: jinja2 (>=2.11.2,<3.0.0)
Requires-Dist: pyjwt (>=1.7.1,<2.0.0)
Requires-Dist: pytest (>=6.2.4,<7.0.0)
Requires-Dist: pytest-custom_exit_code (>=0.3.0,<0.4.0)
Requires-Dist: ruamel.yaml (>=0.16.10,<0.17.0)
